Metadata-Version: 2.1
Name: Cliente
Version: 0.0.3
Summary: Módulo que representa a classe Cliente do sistema bancário
